aemet_mcp/__init__.py
aemet_mcp/server.py
aemet_mcp/res/Beaches_code.json
aemet_mcp/res/Municipallity_code.json
aemet_mcp/res/Provinces_code.json
aemet_mcp/res/Stations_code.json
aemet_mcp-0.3.2.dist-info/licenses/LICENSE
aemet_mcp-0.3.2.dist-info/METADATA
aemet_mcp-0.3.2.dist-info/WHEEL
aemet_mcp-0.3.2.dist-info/entry_points.txt
aemet_mcp-0.3.2.dist-info/top_level.txt
aemet_mcp-0.3.2.dist-info/RECORD
