Metadata-Version: 2.4
Name: aemet_mcp
Version: 0.3.2
Summary: AEMET API integration with MCP (Model Context Protocol)
License-Expression: MIT
Requires-Python: >=3.10
License-File: LICENSE
Requires-Dist: httpx>=0.28.1
Requires-Dist: mcp[cli]>=1.15.0
Dynamic: license-file
